mizan_encoder/__init__.py
mizan_encoder/config.py
mizan_encoder/data.py
mizan_encoder/encoder.py
mizan_encoder/hf_model.py
mizan_encoder/loss.py
mizan_encoder/metrics.py
mizan_encoder/pooling.py
mizan_encoder/train_config.json
mizan_encoder/__pycache__/__init__.cpython-312.pyc
mizan_encoder/__pycache__/__init__.cpython-313.pyc
mizan_encoder/__pycache__/config.cpython-312.pyc
mizan_encoder/__pycache__/config.cpython-313.pyc
mizan_encoder/__pycache__/data.cpython-312.pyc
mizan_encoder/__pycache__/data.cpython-313.pyc
mizan_encoder/__pycache__/encoder.cpython-312.pyc
mizan_encoder/__pycache__/encoder.cpython-313.pyc
mizan_encoder/__pycache__/hf_model.cpython-312.pyc
mizan_encoder/__pycache__/hf_model.cpython-313.pyc
mizan_encoder/__pycache__/loss.cpython-312.pyc
mizan_encoder/__pycache__/loss.cpython-313.pyc
mizan_encoder/__pycache__/metrics.cpython-312.pyc
mizan_encoder/__pycache__/metrics.cpython-313.pyc
mizan_encoder/__pycache__/pooling.cpython-312.pyc
mizan_encoder/__pycache__/pooling.cpython-313.pyc
mizan_encoder/utils/checkpoints.py
mizan_encoder/utils/init.py
mizan_encoder/utils/logging.py
mizan_encoder/utils/seed.py
mizan_encoder-0.1.4.dist-info/METADATA
mizan_encoder-0.1.4.dist-info/WHEEL
mizan_encoder-0.1.4.dist-info/top_level.txt
mizan_encoder-0.1.4.dist-info/RECORD
