Metadata-Version: 2.4
Name: mizan-encoder
Version: 0.1.4
Summary: A scale-aware embedding model and training framework optimized for the Mizan Balance Function.
Author-email: Ahsan Shaokat <your-email@example.com>
License: MIT
Project-URL: Homepage, https://github.com/ahsanshaokat/mizan-encoder
Project-URL: Documentation, https://github.com/ahsanshaokat/mizan-encoder/wiki
Project-URL: Source, https://github.com/ahsanshaokat/mizan-encoder
Project-URL: Tracker, https://github.com/ahsanshaokat/mizan-encoder/issues
Keywords: embeddings,mizan,similarity,vector search,rag,contrastive learning,nlp
Requires-Python: >=3.9
Requires-Dist: torch>=1.10
Requires-Dist: transformers>=4.30
Requires-Dist: numpy
Requires-Dist: scipy
Requires-Dist: tqdm
Requires-Dist: mizan-vector>=0.1.0
